Metadata-Version: 1.0
Name: datachimp
Version: 0.0.1
Summary: Python client to version your data 
Home-page: https://www.modelchimp.com
Author: Samir Madhavan
Author-email: samir.madhavan@gmail.com
License: UNKNOWN
Keywords: modelchimp,ai,datascience,data,versioning
Platform: UNKNOWN
